redu/__init__.py
redu/__main__.py
redu/cli.py
redu/run_redu.py
redu/services/__init__.py
redu/services/ai.py
redu/services/auth.py
redu/services/image.py
redu/services/network.py
redu/services/server.py
redu/services/setup.py
redu/services/ssh.py
redu/services/utils.py
redu/services/whoami.py
redu-1.0.2.dist-info/licenses/LICENSE
redu-1.0.2.dist-info/METADATA
redu-1.0.2.dist-info/WHEEL
redu-1.0.2.dist-info/entry_points.txt
redu-1.0.2.dist-info/top_level.txt
redu-1.0.2.dist-info/RECORD
