Metadata-Version: 2.4
Name: redu
Version: 1.0.2
Summary: Redu Cloud CLI
Home-page: https://redu.cloud
Author: Miloš Živanović
Author-email: Miloš Živanović <office@redu.cloud>
License: MIT
Requires-Python: >=3.8
License-File: LICENSE
Requires-Dist: click>=8.1.7
Requires-Dist: requests>=2.31.0
Requires-Dist: cryptography>=42.0
Dynamic: author
Dynamic: home-page
Dynamic: license-file
Dynamic: requires-python
